LICENSE.txt
MANIFEST.in
README.rst
setup.py
print_json_middleware/__init__.py
print_json_middleware.egg-info/PKG-INFO
print_json_middleware.egg-info/SOURCES.txt
print_json_middleware.egg-info/dependency_links.txt
print_json_middleware.egg-info/entry_points.txt
print_json_middleware.egg-info/not-zip-safe
print_json_middleware.egg-info/top_level.txt