Metadata-Version: 1.1
Name: print-json-middleware
Version: 0.1.1
Summary: JSON prettyprinter WSGI middleware
Home-page: https://github.com/sbrauer/print_json_middleware
Author: Sam Brauer
Author-email: sam.brauer@gmail.com
License: MIT
Platform: UNKNOWN
Classifier: Programming Language :: Python
Classifier: Topic :: Internet :: WWW/HTTP
Classifier: Topic :: Internet :: WWW/HTTP :: WSGI :: Middleware
Classifier: Development Status :: 3 - Alpha
Classifier: License :: OSI Approved :: MIT License
